jupyter_base16_theme/__init__.py
jupyter_base16_theme/_version.py
jupyter_base16_theme/labextension/package.json
jupyter_base16_theme/labextension/static/568.0395f78d69c8fd67538a.js
jupyter_base16_theme/labextension/static/remoteEntry.7a8412680bc6a0523408.js
jupyter_base16_theme/labextension/static/style.js
jupyter_base16_theme/labextension/static/third-party-licenses.json
jupyter_base16_theme/labextension/themes/jupyter_base16_theme/cd5c21dfecad1bf39296a3649056f8c59115c383ade9c3c43ca344ca11bbd809.ttf
jupyter_base16_theme/labextension/themes/jupyter_base16_theme/index.css
jupyter_base16_theme/labextension/themes/jupyter_base16_theme/index.js
jupyter_base16_theme-0.0.12.data/data/share/jupyter/labextensions/jupyter_base16_theme/install.json
jupyter_base16_theme-0.0.12.data/data/share/jupyter/labextensions/jupyter_base16_theme/package.json
jupyter_base16_theme-0.0.12.data/data/share/jupyter/labextensions/jupyter_base16_theme/static/568.0395f78d69c8fd67538a.js
jupyter_base16_theme-0.0.12.data/data/share/jupyter/labextensions/jupyter_base16_theme/static/remoteEntry.7a8412680bc6a0523408.js
jupyter_base16_theme-0.0.12.data/data/share/jupyter/labextensions/jupyter_base16_theme/static/style.js
jupyter_base16_theme-0.0.12.data/data/share/jupyter/labextensions/jupyter_base16_theme/static/third-party-licenses.json
jupyter_base16_theme-0.0.12.data/data/share/jupyter/labextensions/jupyter_base16_theme/themes/jupyter_base16_theme/cd5c21dfecad1bf39296a3649056f8c59115c383ade9c3c43ca344ca11bbd809.ttf
jupyter_base16_theme-0.0.12.data/data/share/jupyter/labextensions/jupyter_base16_theme/themes/jupyter_base16_theme/index.css
jupyter_base16_theme-0.0.12.data/data/share/jupyter/labextensions/jupyter_base16_theme/themes/jupyter_base16_theme/index.js
jupyter_base16_theme-0.0.12.dist-info/LICENSE
jupyter_base16_theme-0.0.12.dist-info/METADATA
jupyter_base16_theme-0.0.12.dist-info/WHEEL
jupyter_base16_theme-0.0.12.dist-info/top_level.txt
jupyter_base16_theme-0.0.12.dist-info/RECORD
